whitebit/__init__.py
whitebit/__version__.py
whitebit/client.py
whitebit/collateral/__init__.py
whitebit/collateral/account/__init__.py
whitebit/collateral/account/account.py
whitebit/collateral/market/__init__.py
whitebit/collateral/market/market.py
whitebit/collateral/order/__init__.py
whitebit/collateral/order/order.py
whitebit/main/__init__.py
whitebit/main/account/__init__.py
whitebit/main/account/account.py
whitebit/stream/__init__.py
whitebit/stream/ws.py
whitebit/trade/__init__.py
whitebit/trade/account/__init__.py
whitebit/trade/account/account.py
whitebit/trade/market/__init__.py
whitebit/trade/market/market.py
whitebit/trade/order/__init__.py
whitebit/trade/order/order.py
python_whitebit_sdk-1.0.5.dist-info/LICENSE
python_whitebit_sdk-1.0.5.dist-info/METADATA
python_whitebit_sdk-1.0.5.dist-info/WHEEL
python_whitebit_sdk-1.0.5.dist-info/top_level.txt
python_whitebit_sdk-1.0.5.dist-info/RECORD
