Metadata-Version: 2.1
Name: python-whitebit-sdk
Version: 1.0.5
Summary: Clients and methods to interact with the Whitebit exchange.
Home-page: https://github.com/whitebit-exchange/python-sdk
Author: UAB Clear White Technologies
Author-email: support@whitebit.com
License: MIT
Classifier: License :: OSI Approved :: MIT License
Classifier: Programming Language :: Python
Classifier: Programming Language :: Python :: 3.10
Classifier: Development Status :: 5 - Production/Stable
Classifier: Framework :: AsyncIO
Classifier: Natural Language :: English
Classifier: Operating System :: MacOS
Classifier: Operating System :: Unix
Classifier: Operating System :: Microsoft :: Windows
Requires-Python: >=3.10.0
License-File: LICENSE
Requires-Dist: websockets (>=10.4.0)
Requires-Dist: asyncio (>=3.4)
Requires-Dist: requests (>=2.28.1)
Requires-Dist: responses (>=0.23.1)
Requires-Dist: urllib3 (==1.26.15)
Provides-Extra: testing
Requires-Dist: pytest ; extra == 'testing'
Requires-Dist: tqdm ; extra == 'testing'
